Workbook

Sheet Setup
A1: FLY GACA — Budget vs Actual Tracker — Setup
A3: Fiscal Year: | B3: FY2026-27 (Apr 2026 – Mar 2027)
A4: Currency: | B4: SAR primary | 1 USD = 3.75 SAR reference
A5: Last Updated: | B5: May 2026
A6: Owner: | B6: Captain Adel Yahya A. Madkhali — Founder
A8: COST CENTERS | B8: Owner | C8: Department | D8: Notes
A9: CC-ENG | B9: Captain Adel / CTO (TBH) | C9: Engineering | D9: API, cloud, dev salaries
A10: CC-PROD | B10: Captain Adel | C10: Product | D10: Design, UX, product management
A11: CC-MKT | B11: Captain Adel / CMO (TBH) | C11: Marketing & GTM | D11: Digital ads, events, content
A12: CC-CS | B12: Captain Adel / CS Lead (TBH) | C12: Customer Success | D12: Onboarding, support, retention
A13: CC-OPS | B13: Captain Adel / COO (TBH) | C13: Operations & Admin | D13: Office, legal, compliance
A14: CC-FIN | B14: Captain Adel / CFO (TBH) | C14: Finance | D14: Accounting, audit, banking
A15: CC-REV | B15: Captain Adel | C15: Revenue | D15: All revenue lines consolidated

Sheet Annual Budget
A1: FLY GACA — Annual Budget FY2026-27
A2: All figures in SAR | Import from approved budget model | Lock after board approval
A3: Account Code | B3: Account Name | C3: Cost Center | D3: Annual Total | E3: Apr-26 | F3: May-26 | G3: Jun-26 | H3: Jul-26 | I3: Aug-26 | J3: Sep-26 | K3: Oct-26 | L3: Nov-26 | M3: Dec-26 | N3: Jan-27 | O3: Feb-27 | P3: Mar-27
A4: REVENUE
A5: 4100 | B5: Pro Subscriptions — Monthly | C5: CC-REV | D5: 970000 | E5: 50000 | F5: 55000 | G5: 60000 | H5: 65000 | I5: 70000 | J5: 75000 | K5: 82000 | L5: 88000 | M5: 95000 | N5: 102000 | O5: 110000 | P5: 118000
A6: 4110 | B6: Pro Subscriptions — Annual | C6: CC-REV | D6: 316000 | E6: 20000 | F6: 20000 | G6: 22000 | H6: 22000 | I6: 25000 | J6: 25000 | K6: 28000 | L6: 28000 | M6: 30000 | N6: 30000 | O6: 33000 | P6: 33000
A7: 4200 | B7: Academy Contracts — B2B | C7: CC-REV | D7: 1260000 | E7: 80000 | F7: 80000 | G7: 90000 | H7: 90000 | I7: 100000 | J7: 100000 | K7: 110000 | L7: 110000 | M7: 120000 | N7: 120000 | O7: 130000 | P7: 130000
A8: 4300 | B8: White-Label Licensing | C8: CC-REV | D8: 270000 | E8: 0 | F8: 0 | G8: 0 | H8: 25000 | I8: 25000 | J8: 25000 | K8: 30000 | L8: 30000 | M8: 30000 | N8: 35000 | O8: 35000 | P8: 35000
A9: 4400 | B9: Other Income | C9: CC-REV | D9: 60000 | E9: 5000 | F9: 5000 | G9: 5000 | H9: 5000 | I9: 5000 | J9: 5000 | K9: 5000 | L9: 5000 | M9: 5000 | N9: 5000 | O9: 5000 | P9: 5000
A10: COST OF GOODS SOLD (COGS)
A11: 5100 | B11: COGS — Gemini API | C11: CC-ENG | D11: 349200 | E11: 18000 | F11: 19800 | G11: 21600 | H11: 23400 | I11: 25200 | J11: 27000 | K11: 29520 | L11: 31680 | M11: 34200 | N11: 36720 | O11: 39600 | P11: 42480
A12: 5110 | B12: COGS — Firebase Hosting | C12: CC-ENG | D12: 155200 | E12: 8000 | F12: 8800 | G12: 9600 | H12: 10400 | I12: 11200 | J12: 12000 | K12: 13120 | L12: 14080 | M12: 15200 | N12: 16320 | O12: 17600 | P12: 18880
A13: 5120 | B13: COGS — Moyasar Fees | C13: CC-REV | D13: 82572 | E13: 4050 | F13: 4455 | G13: 4860 | H13: 5643 | I13: 6048 | J13: 6453 | K13: 7128 | L13: 7614 | M13: 8168 | N13: 8722 | O13: 9477 | P13: 9954
A14: PERSONNEL COSTS
A15: 5200 | B15: Salaries — Engineering | C15: CC-ENG | D15: 1080000 | E15: 90000 | F15: 90000 | G15: 90000 | H15: 90000 | I15: 90000 | J15: 90000 | K15: 90000 | L15: 90000 | M15: 90000 | N15: 90000 | O15: 90000 | P15: 90000
A16: 5210 | B16: Salaries — Founder | C16: CC-OPS | D16: 300000 | E16: 25000 | F16: 25000 | G16: 25000 | H16: 25000 | I16: 25000 | J16: 25000 | K16: 25000 | L16: 25000 | M16: 25000 | N16: 25000 | O16: 25000 | P16: 25000
A17: 5220 | B17: Salaries — Customer Success | C17: CC-CS | D17: 198000 | E17: 15000 | F17: 15000 | G17: 15000 | H17: 15000 | I17: 15000 | J17: 15000 | K17: 18000 | L17: 18000 | M17: 18000 | N17: 18000 | O17: 18000 | P17: 18000
A18: 5230 | B18: Salaries — Marketing | C18: CC-MKT | D18: 162000 | E18: 12000 | F18: 12000 | G18: 12000 | H18: 12000 | I18: 12000 | J18: 12000 | K18: 15000 | L18: 15000 | M18: 15000 | N18: 15000 | O18: 15000 | P18: 15000
A19: OPERATING EXPENSES
A20: 5300 | B20: GOSI — Employer Contribution | C20: CC-OPS | D20: 213120 | E20: 17040 | F20: 17040 | G20: 17040 | H20: 17040 | I20: 17040 | J20: 17040 | K20: 18480 | L20: 18480 | M20: 18480 | N20: 18480 | O20: 18480 | P20: 18480
A21: 5400 | B21: Marketing & GTM | C21: CC-MKT | D21: 380000 | E21: 20000 | F21: 20000 | G21: 25000 | H21: 25000 | I21: 30000 | J21: 30000 | K21: 35000 | L21: 35000 | M21: 40000 | N21: 40000 | O21: 40000 | P21: 40000
A22: 5500 | B22: Office Rent | C22: CC-OPS | D22: 96000 | E22: 8000 | F22: 8000 | G22: 8000 | H22: 8000 | I22: 8000 | J22: 8000 | K22: 8000 | L22: 8000 | M22: 8000 | N22: 8000 | O22: 8000 | P22: 8000
A23: 5600 | B23: Software & SaaS Tools | C23: CC-ENG | D23: 66000 | E23: 5000 | F23: 5000 | G23: 5000 | H23: 5000 | I23: 5000 | J23: 5000 | K23: 6000 | L23: 6000 | M23: 6000 | N23: 6000 | O23: 6000 | P23: 6000
A24: 5700 | B24: Legal & Professional Fees | C24: CC-FIN | D24: 70000 | E24: 10000 | F24: 5000 | G24: 5000 | H24: 5000 | I24: 5000 | J24: 5000 | K24: 5000 | L24: 5000 | M24: 5000 | N24: 10000 | O24: 5000 | P24: 5000
A25: 5800 | B25: Travel & Entertainment | C25: CC-OPS | D25: 69000 | E25: 5000 | F25: 5000 | G25: 5000 | H25: 8000 | I25: 5000 | J25: 5000 | K25: 8000 | L25: 5000 | M25: 5000 | N25: 8000 | O25: 5000 | P25: 5000
A26: 5900 | B26: Other Operating Expenses | C26: CC-OPS | D26: 36000 | E26: 3000 | F26: 3000 | G26: 3000 | H26: 3000 | I26: 3000 | J26: 3000 | K26: 3000 | L26: 3000 | M26: 3000 | N26: 3000 | O26: 3000 | P26: 3000

Sheet Actuals
A1: FLY GACA — Monthly Actuals FY2026-27
A2: INSTRUCTION: Import actuals from accounting system (Zoho Books / QuickBooks) by Day 16 of each month-end close. Map to CoA codes in column A.
A3: Account Code | B3: Account Name | C3: Cost Center | D3: YTD Actual | E3: Apr-26 | F3: May-26 | G3: Jun-26 | H3: Jul-26 | I3: Aug-26 | J3: Sep-26 | K3: Oct-26 | L3: Nov-26 | M3: Dec-26 | N3: Jan-27 | O3: Feb-27 | P3: Mar-27
A4: REVENUE
A5: 4100 | B5: Pro Subscriptions — Monthly | C5: CC-REV | D5: 99254 | E5: 52091 | F5: 47163
A6: 4110 | B6: Pro Subscriptions — Annual | C6: CC-REV | D6: 36989 | E6: 18650 | F6: 18339
A7: 4200 | B7: Academy Contracts — B2B | C7: CC-REV | D7: 169916 | E7: 85675 | F7: 84241
A8: 4300 | B8: White-Label Licensing | C8: CC-REV | D8: 0 | E8: 0 | F8: 0
A9: 4400 | B9: Other Income | C9: CC-REV | D9: 9178 | E9: 4883 | F9: 4295
A10: COST OF GOODS SOLD (COGS)
A11: 5100 | B11: COGS — Gemini API | C11: CC-ENG | D11: 36313 | E11: 16481 | F11: 19832
A12: 5110 | B12: COGS — Firebase Hosting | C12: CC-ENG | D12: 14869 | E12: 6864 | F12: 8005
A13: 5120 | B13: COGS — Moyasar Fees | C13: CC-REV | D13: 8747 | E13: 4232 | F13: 4515
A14: PERSONNEL COSTS
A15: 5200 | B15: Salaries — Engineering | C15: CC-ENG | D15: 174862 | E15: 82452 | F15: 92410
A16: 5210 | B16: Salaries — Founder | C16: CC-OPS | D16: 48620 | E16: 27321 | F16: 21299
A17: 5220 | B17: Salaries — Customer Success | C17: CC-CS | D17: 32268 | E17: 16376 | F17: 15892
A18: 5230 | B18: Salaries — Marketing | C18: CC-MKT | D18: 22185 | E18: 11425 | F18: 10760
A19: OPERATING EXPENSES
A20: 5300 | B20: GOSI — Employer Contribution | C20: CC-OPS | D20: 35582 | E20: 19377 | F20: 16205
A21: 5400 | B21: Marketing & GTM | C21: CC-MKT | D21: 35136 | E21: 17556 | F21: 17580
A22: 5500 | B22: Office Rent | C22: CC-OPS | D22: 17083 | E22: 8834 | F22: 8249
A23: 5600 | B23: Software & SaaS Tools | C23: CC-ENG | D23: 10806 | E23: 5461 | F23: 5345
A24: 5700 | B24: Legal & Professional Fees | C24: CC-FIN | D24: 15819 | E24: 10109 | F24: 5710
A25: 5800 | B25: Travel & Entertainment | C25: CC-OPS | D25: 9896 | E25: 4818 | F25: 5078
A26: 5900 | B26: Other Operating Expenses | C26: CC-OPS | D26: 6403 | E26: 3296 | F26: 3107

Sheet Variance
A1: FLY GACA — Budget vs Actual Variance Analysis FY2026-27
A2: Green = within 5% | Amber = 5-10% over | Red = >10% over budget | Positive variance (revenue) = favorable
A3: Code | B3: Account | C3: CC | D3: Budget YTD | E3: Actual YTD | F3: Variance (SAR) | G3: Variance % | H3: Apr-26 Budget | I3: May-26 Budget | J3: Jun-26 Budget | K3: Jul-26 Budget | L3: Aug-26 Budget | M3: Sep-26 Budget
A4: REVENUE
A5: 4100 | B5: Pro Subscriptions — Monthly | C5: CC-REV | D5: ='Annual Budget'!E5+'Annual Budget'!F5 | E5: =Actuals!E5+IF(ISNUMBER(Actuals!F5),Actuals!F5,0) | F5: =E5-D5 | G5: =IF(D5<>0,E5/D5-1,0) | H5: 50000 | I5: 55000 | J5: 60000 | K5: 65000 | L5: 70000 | M5: 75000
A6: 4110 | B6: Pro Subscriptions — Annual | C6: CC-REV | D6: ='Annual Budget'!E6+'Annual Budget'!F6 | E6: =Actuals!E6+IF(ISNUMBER(Actuals!F6),Actuals!F6,0) | F6: =E6-D6 | G6: =IF(D6<>0,E6/D6-1,0) | H6: 20000 | I6: 20000 | J6: 22000 | K6: 22000 | L6: 25000 | M6: 25000
A7: 4200 | B7: Academy Contracts — B2B | C7: CC-REV | D7: ='Annual Budget'!E7+'Annual Budget'!F7 | E7: =Actuals!E7+IF(ISNUMBER(Actuals!F7),Actuals!F7,0) | F7: =E7-D7 | G7: =IF(D7<>0,E7/D7-1,0) | H7: 80000 | I7: 80000 | J7: 90000 | K7: 90000 | L7: 100000 | M7: 100000
A8: 4300 | B8: White-Label Licensing | C8: CC-REV | D8: ='Annual Budget'!E8+'Annual Budget'!F8 | E8: =Actuals!E8+IF(ISNUMBER(Actuals!F8),Actuals!F8,0) | F8: =E8-D8 | G8: =IF(D8<>0,E8/D8-1,0) | H8: 0 | I8: 0 | J8: 0 | K8: 25000 | L8: 25000 | M8: 25000
A9: 4400 | B9: Other Income | C9: CC-REV | D9: ='Annual Budget'!E9+'Annual Budget'!F9 | E9: =Actuals!E9+IF(ISNUMBER(Actuals!F9),Actuals!F9,0) | F9: =E9-D9 | G9: =IF(D9<>0,E9/D9-1,0) | H9: 5000 | I9: 5000 | J9: 5000 | K9: 5000 | L9: 5000 | M9: 5000
A10: COST OF GOODS SOLD (COGS)
A11: 5100 | B11: COGS — Gemini API | C11: CC-ENG | D11: ='Annual Budget'!E11+'Annual Budget'!F11 | E11: =Actuals!E11+IF(ISNUMBER(Actuals!F11),Actuals!F11,0) | F11: =E11-D11 | G11: =IF(D11<>0,E11/D11-1,0) | H11: 18000 | I11: 19800 | J11: 21600 | K11: 23400 | L11: 25200 | M11: 27000
A12: 5110 | B12: COGS — Firebase Hosting | C12: CC-ENG | D12: ='Annual Budget'!E12+'Annual Budget'!F12 | E12: =Actuals!E12+IF(ISNUMBER(Actuals!F12),Actuals!F12,0) | F12: =E12-D12 | G12: =IF(D12<>0,E12/D12-1,0) | H12: 8000 | I12: 8800 | J12: 9600 | K12: 10400 | L12: 11200 | M12: 12000
A13: 5120 | B13: COGS — Moyasar Fees | C13: CC-REV | D13: ='Annual Budget'!E13+'Annual Budget'!F13 | E13: =Actuals!E13+IF(ISNUMBER(Actuals!F13),Actuals!F13,0) | F13: =E13-D13 | G13: =IF(D13<>0,E13/D13-1,0) | H13: 4050 | I13: 4455 | J13: 4860 | K13: 5643 | L13: 6048 | M13: 6453
A14: PERSONNEL COSTS
A15: 5200 | B15: Salaries — Engineering | C15: CC-ENG | D15: ='Annual Budget'!E15+'Annual Budget'!F15 | E15: =Actuals!E15+IF(ISNUMBER(Actuals!F15),Actuals!F15,0) | F15: =E15-D15 | G15: =IF(D15<>0,E15/D15-1,0) | H15: 90000 | I15: 90000 | J15: 90000 | K15: 90000 | L15: 90000 | M15: 90000
A16: 5210 | B16: Salaries — Founder | C16: CC-OPS | D16: ='Annual Budget'!E16+'Annual Budget'!F16 | E16: =Actuals!E16+IF(ISNUMBER(Actuals!F16),Actuals!F16,0) | F16: =E16-D16 | G16: =IF(D16<>0,E16/D16-1,0) | H16: 25000 | I16: 25000 | J16: 25000 | K16: 25000 | L16: 25000 | M16: 25000
A17: 5220 | B17: Salaries — Customer Success | C17: CC-CS | D17: ='Annual Budget'!E17+'Annual Budget'!F17 | E17: =Actuals!E17+IF(ISNUMBER(Actuals!F17),Actuals!F17,0) | F17: =E17-D17 | G17: =IF(D17<>0,E17/D17-1,0) | H17: 15000 | I17: 15000 | J17: 15000 | K17: 15000 | L17: 15000 | M17: 15000
A18: 5230 | B18: Salaries — Marketing | C18: CC-MKT | D18: ='Annual Budget'!E18+'Annual Budget'!F18 | E18: =Actuals!E18+IF(ISNUMBER(Actuals!F18),Actuals!F18,0) | F18: =E18-D18 | G18: =IF(D18<>0,E18/D18-1,0) | H18: 12000 | I18: 12000 | J18: 12000 | K18: 12000 | L18: 12000 | M18: 12000
A19: OPERATING EXPENSES
A20: 5300 | B20: GOSI — Employer Contribution | C20: CC-OPS | D20: ='Annual Budget'!E20+'Annual Budget'!F20 | E20: =Actuals!E20+IF(ISNUMBER(Actuals!F20),Actuals!F20,0) | F20: =E20-D20 | G20: =IF(D20<>0,E20/D20-1,0) | H20: 17040 | I20: 17040 | J20: 17040 | K20: 17040 | L20: 17040 | M20: 17040
A21: 5400 | B21: Marketing & GTM | C21: CC-MKT | D21: ='Annual Budget'!E21+'Annual Budget'!F21 | E21: =Actuals!E21+IF(ISNUMBER(Actuals!F21),Actuals!F21,0) | F21: =E21-D21 | G21: =IF(D21<>0,E21/D21-1,0) | H21: 20000 | I21: 20000 | J21: 25000 | K21: 25000 | L21: 30000 | M21: 30000
A22: 5500 | B22: Office Rent | C22: CC-OPS | D22: ='Annual Budget'!E22+'Annual Budget'!F22 | E22: =Actuals!E22+IF(ISNUMBER(Actuals!F22),Actuals!F22,0) | F22: =E22-D22 | G22: =IF(D22<>0,E22/D22-1,0) | H22: 8000 | I22: 8000 | J22: 8000 | K22: 8000 | L22: 8000 | M22: 8000
A23: 5600 | B23: Software & SaaS Tools | C23: CC-ENG | D23: ='Annual Budget'!E23+'Annual Budget'!F23 | E23: =Actuals!E23+IF(ISNUMBER(Actuals!F23),Actuals!F23,0) | F23: =E23-D23 | G23: =IF(D23<>0,E23/D23-1,0) | H23: 5000 | I23: 5000 | J23: 5000 | K23: 5000 | L23: 5000 | M23: 5000
A24: 5700 | B24: Legal & Professional Fees | C24: CC-FIN | D24: ='Annual Budget'!E24+'Annual Budget'!F24 | E24: =Actuals!E24+IF(ISNUMBER(Actuals!F24),Actuals!F24,0) | F24: =E24-D24 | G24: =IF(D24<>0,E24/D24-1,0) | H24: 10000 | I24: 5000 | J24: 5000 | K24: 5000 | L24: 5000 | M24: 5000
A25: 5800 | B25: Travel & Entertainment | C25: CC-OPS | D25: ='Annual Budget'!E25+'Annual Budget'!F25 | E25: =Actuals!E25+IF(ISNUMBER(Actuals!F25),Actuals!F25,0) | F25: =E25-D25 | G25: =IF(D25<>0,E25/D25-1,0) | H25: 5000 | I25: 5000 | J25: 5000 | K25: 8000 | L25: 5000 | M25: 5000
A26: 5900 | B26: Other Operating Expenses | C26: CC-OPS | D26: ='Annual Budget'!E26+'Annual Budget'!F26 | E26: =Actuals!E26+IF(ISNUMBER(Actuals!F26),Actuals!F26,0) | F26: =E26-D26 | G26: =IF(D26<>0,E26/D26-1,0) | H26: 3000 | I26: 3000 | J26: 3000 | K26: 3000 | L26: 3000 | M26: 3000

Sheet Commentary
A1: FLY GACA — Variance Commentary FY2026-27
A2: Add one row per significant variance (>5% or >5,000 SAR). Update by Day 19 of month-end close. Shared in board pack.
A3: Month | B3: Account Code | C3: Account Name | D3: Variance SAR | E3: Variance % | F3: Explanation & Action
A4: Apr-26 | B4: 5400 | C4: Marketing & GTM | D4: -8500 | E4: -0.43 | F4: Planned campaign delayed to May-26 awaiting creative assets. Budget not spent will roll to May. No annual impact expected.
A5: Apr-26 | B5: 5100 | C5: COGS — Gemini API | D5: 3200 | E5: 0.18 | F5: Higher than budgeted API calls due to beta testing with 3 academy partners. Usage will normalize in May. Monitoring daily.
A6: Apr-26 | B6: 4100 | C6: Pro Subscriptions — Monthly | D6: 4750 | E6: 0.1 | F6: Outperformed budget due to early adoption from GACA-affiliated flight schools. Positive variance — no action required.
A7: May-26 | B7: 5400 | C7: Marketing & GTM | D7: 12000 | E7: 0.6 | F7: April campaign budget rolled to May as planned. Combined April+May spend is on track vs. 2-month budget total.
